client.py
py_get_sequence_api_client-0.1.0.dist-info/licenses/LICENSE
py_get_sequence_api_client-0.1.0.dist-info/METADATA
py_get_sequence_api_client-0.1.0.dist-info/WHEEL
py_get_sequence_api_client-0.1.0.dist-info/top_level.txt
py_get_sequence_api_client-0.1.0.dist-info/RECORD
