Metadata-Version: 2.4
Name: py_get_sequence_api_client
Version: 0.1.0
Summary: Async Python client for Sequence financial orchestration platform API.
Author-email: Dyllan Macias <DellanX@Live.com>
License: MIT License
Project-URL: Homepage, https://github.com/DellanX/py_get_sequence_api_client
Project-URL: Source, https://github.com/DellanX/py_get_sequence_api_client
Requires-Python: >=3.10
License-File: LICENSE
Requires-Dist: aiohttp>=3.8.0
Provides-Extra: test
Requires-Dist: pytest; extra == "test"
Requires-Dist: pytest-cov; extra == "test"
Requires-Dist: pytest-asyncio; extra == "test"
Dynamic: license-file
